CHANGELOG.txt
LICENSE.txt
MANIFEST.in
README.txt
setup.py
cnyao_calculator/__init__.py
cnyao_calculator.egg-info/PKG-INFO
cnyao_calculator.egg-info/SOURCES.txt
cnyao_calculator.egg-info/dependency_links.txt
cnyao_calculator.egg-info/top_level.txt